.gitignore
.pre-commit-config.yaml
.readthedocs.yaml
.zenodo.json
CHANGELOG.rst
CODE_OF_CONDUCT.md
LICENSE.txt
README.rst
pyproject.toml
setup.cfg
.github/ISSUE_TEMPLATE/bug_report.md
.github/ISSUE_TEMPLATE/feature_request.md
.github/ISSUE_TEMPLATE/keyword_issue.md
.github/ISSUE_TEMPLATE/text-improvement.md
.github/workflows/codestyle.yml
.github/workflows/docs.yml
.github/workflows/release.yml
.github/workflows/test-release.yml
.github/workflows/testing.yml
docs/Makefile
docs/api.rst
docs/appendix.rst
docs/citation.rst
docs/conf.py
docs/index.rst
docs/keyword_processor.py
docs/make.bat
docs/references.md
docs/solarnet-emails.txt
docs/_static/class_new_highlight.css
docs/_static/custom.css
docs/_static/fits_coordinate_calculation_flowchart.png
docs/_static/wide_navbar.css
docs/dev-guide/code_standards.rst
docs/dev-guide/docs.rst
docs/dev-guide/index.rst
docs/dev-guide/maintainer_workflow.rst
docs/dev-guide/tests.rst
docs/dev-guide/version_guidelines.rst
docs/logo/favicon.ico
docs/logo/logo.png
docs/source/appendix-1.md
docs/source/appendix-2.md
docs/source/appendix-3.md
docs/source/appendix-4.md
docs/source/appendix-5.md
docs/source/appendix-6.md
docs/source/appendix-7.md
docs/source/appendix-8.md
docs/source/appendix-9.md
docs/source/parta.md
docs/source/partb.md
docs/source/partc.md
docs/user-guide/acknowledging.rst
docs/user-guide/index.rst
docs/user-guide/install_guide.rst
docs/user-guide/solarnet_schema_customization.rst
docs/user-guide/templates.rst
docs/user-guide/validation.rst
docs/whatsnew/index.rst
solarnet_metadata/__init__.py
solarnet_metadata/_version.py
solarnet_metadata/schema.py
solarnet_metadata/util.py
solarnet_metadata/validation.py
solarnet_metadata.egg-info/PKG-INFO
solarnet_metadata.egg-info/SOURCES.txt
solarnet_metadata.egg-info/dependency_links.txt
solarnet_metadata.egg-info/requires.txt
solarnet_metadata.egg-info/top_level.txt
solarnet_metadata/data/README.rst
solarnet_metadata/data/SOLARNET_attr_schema.yaml
solarnet_metadata/tests/__init__.py
solarnet_metadata/tests/test_schema.py
solarnet_metadata/tests/test_validation.py